infinyon_coagent_client/__init__.py
infinyon_coagent_client/client.py
infinyon_coagent_client/logapi.py
infinyon_coagent_client/py.typed
infinyon_coagent_client-0.6.0.dist-info/WHEEL
infinyon_coagent_client-0.6.0.dist-info/METADATA
infinyon_coagent_client-0.6.0.dist-info/RECORD
